dgsender/__init__.py
dgsender/async_email_sender.py
dgsender/async_sender.py
dgsender/async_slack_sender.py
dgsender/async_telegram_sender.py
dgsender/base.py
dgsender/composite_sender.py
dgsender/email_sender.py
dgsender/exceptions.py
dgsender/mailer.py
dgsender/metrics.py
dgsender/slack_sender.py
dgsender/telegram_sender.py
dgsender/zabbix_sender.py
dgsender-1.0.0a2.dist-info/licenses/LICENSE
dgsender-1.0.0a2.dist-info/METADATA
dgsender-1.0.0a2.dist-info/WHEEL
dgsender-1.0.0a2.dist-info/top_level.txt
dgsender-1.0.0a2.dist-info/RECORD
