Metadata-Version: 2.4
Name: dgsender
Version: 1.0.0a2
Summary: Unified sender package for email, telegram, slack and zabbix with async support.
Author-email: Roman Rasputin <admin@roro.su>
License: MIT License
Project-URL: Homepage, https://gitlab.com/gng-group/dgsender
Project-URL: BugTracker, https://gitlab.com/gng-group/dgsender/issues
Keywords: telegram,email,zabbix
Classifier: Development Status :: 4 - Beta
Classifier: Intended Audience :: Developers
Classifier: License :: OSI Approved :: MIT License
Classifier: Programming Language :: Python :: 3.10
Classifier: Programming Language :: Python :: 3.11
Classifier: Programming Language :: Python :: 3.12
Classifier: Programming Language :: Python :: 3.13
Classifier: Operating System :: OS Independent
Classifier: Topic :: Software Development :: Libraries :: Python Modules
Classifier: Topic :: System :: Distributed Computing
Requires-Python: >=3.10
License-File: LICENSE
Requires-Dist: requests>=2.25.0
Provides-Extra: mail
Provides-Extra: tg
Requires-Dist: requests>=2.25.0; extra == "tg"
Provides-Extra: zabbix
Requires-Dist: divinegift>=1.3.16; extra == "zabbix"
Provides-Extra: slack
Requires-Dist: requests>=2.25.0; extra == "slack"
Provides-Extra: async-mail
Provides-Extra: async-tg
Requires-Dist: aiohttp>=3.8.0; extra == "async-tg"
Provides-Extra: async-slack
Requires-Dist: aiohttp>=3.8.0; extra == "async-slack"
Provides-Extra: metrics
Requires-Dist: dgmetrics>=1.0.0a7; extra == "metrics"
Provides-Extra: all
Requires-Dist: requests>=2.25.0; extra == "all"
Requires-Dist: aiohttp>=3.8.0; extra == "all"
Requires-Dist: dgmetrics>=1.0.0a7; extra == "all"
Dynamic: license-file
